django_locations_base-0.3.4.dist-info/.DS_Store
django_locations_base-0.3.4.dist-info/DESCRIPTION.rst
django_locations_base-0.3.4.dist-info/METADATA
django_locations_base-0.3.4.dist-info/metadata.json
django_locations_base-0.3.4.dist-info/RECORD
django_locations_base-0.3.4.dist-info/top_level.txt
django_locations_base-0.3.4.dist-info/WHEEL
locations/__init__.py
locations/admin.py
locations/choices.py
locations/forms.py
locations/models.py
locations/tests.py
locations/utils.py
locations/migrations/0001_initial.py
locations/migrations/__init__.py
locations/south_migrations/0001_initial.py
locations/south_migrations/0002_auto__add_field_location_slug.py
locations/south_migrations/0003_auto__add_field_location_default_location.py
locations/south_migrations/__init__.py
